LICENSE
README.md
setup.cfg
setup.py
marvmiloTools/__init__.py
marvmiloTools/dictionary_tools.py
marvmiloTools/json_tools.py
marvmiloTools.egg-info/PKG-INFO
marvmiloTools.egg-info/SOURCES.txt
marvmiloTools.egg-info/dependency_links.txt
marvmiloTools.egg-info/requires.txt
marvmiloTools.egg-info/top_level.txt
marvmiloTools/dash_tools/__init__.py
marvmiloTools/dash_tools/browsertime.py
marvmiloTools/dash_tools/nav/__init__.py
marvmiloTools/dash_tools/nav/item.py