Metadata-Version: 2.1
Name: marvmiloTools
Version: 1.11.3
Summary: Tools for using on diffrent Platforms
Home-page: https://github.com/marvmilo/marvmiloTools
Author: marvmilo
Author-email: marvin.milojevic@gmail.com
License: MIT
Download-URL: https://github.com/marvmilo/marvmiloTools/archive/refs/tags/v1.11.3.tar.gz
Keywords: Tools
Platform: UNKNOWN
Classifier: Development Status :: 3 - Alpha
Classifier: Intended Audience :: Developers
Classifier: Topic :: Software Development :: Build Tools
Classifier: License :: OSI Approved :: MIT License
Classifier: Programming Language :: Python :: 3
Classifier: Programming Language :: Python :: 3.4
Classifier: Programming Language :: Python :: 3.5
Classifier: Programming Language :: Python :: 3.6
Classifier: Programming Language :: Python :: 3.7
Classifier: Programming Language :: Python :: 3.8
Classifier: Programming Language :: Python :: 3.9
License-File: LICENSE
